mike/__init__.py
mike/battle_listener.py
mike/bot.py
mike/client.py
mike/constants.py
mike/db.py
mike/embeds.py
mike/units.py
drugwars_mike-0.1.7.dist-info/LICENSE
drugwars_mike-0.1.7.dist-info/METADATA
drugwars_mike-0.1.7.dist-info/WHEEL
drugwars_mike-0.1.7.dist-info/entry_points.txt
drugwars_mike-0.1.7.dist-info/top_level.txt
drugwars_mike-0.1.7.dist-info/RECORD
