Metadata-Version: 2.1
Name: drugwars-mike
Version: 0.1.7
Summary: A discord bot to notify battles
Home-page: http://github.com/emre/mike
Author: emre yilmaz
Author-email: mail@emreyilmaz.me
License: MIT
Platform: UNKNOWN
Requires-Dist: dataset
Requires-Dist: discord.py
Requires-Dist: aioredis
Requires-Dist: steem
Requires-Dist: aiomysql
